binary_equalab/__init__.py
binary_equalab/cli.py
binary_equalab/engine.py
binary_equalab/functions.py
binary_equalab/geometry.py
binary_equalab/giac_poc.py
binary_equalab/parser_enhanced.py
binary_equalab/shell_setup.py
binary_equalab/sonify.py
binary_equalab-2.0.2.dist-info/METADATA
binary_equalab-2.0.2.dist-info/WHEEL
binary_equalab-2.0.2.dist-info/entry_points.txt
binary_equalab-2.0.2.dist-info/RECORD
