Metadata-Version: 2.4
Name: binary-equalab
Version: 2.0.2
Summary: Advanced Algebra & Calculus CLI Tool
Project-URL: Homepage, https://github.com/Malexnnn/BinaryEquaLab
Project-URL: Repository, https://github.com/Malexnnn/BinaryEquaLab
Project-URL: Documentation, https://github.com/Malexnnn/BinaryEquaLab#readme
Author-email: Malexnnn <carde@example.com>
License-Expression: MIT
Keywords: algebra,calculator,calculus,cas,math,spanish,symbolic
Classifier: Development Status :: 4 - Beta
Classifier: Environment :: Console
Classifier: Intended Audience :: Education
Classifier: Intended Audience :: Science/Research
Classifier: License :: OSI Approved :: MIT License
Classifier: Operating System :: OS Independent
Classifier: Programming Language :: Python :: 3
Classifier: Programming Language :: Python :: 3.9
Classifier: Programming Language :: Python :: 3.10
Classifier: Programming Language :: Python :: 3.11
Classifier: Programming Language :: Python :: 3.12
Classifier: Topic :: Scientific/Engineering :: Mathematics
Requires-Python: >=3.9
Requires-Dist: numpy>=1.24
Requires-Dist: prompt-toolkit>=3.0
Requires-Dist: rich>=13.0
Requires-Dist: sympy>=1.12
Provides-Extra: dev
Requires-Dist: black>=23.0; extra == 'dev'
Requires-Dist: mypy>=1.0; extra == 'dev'
Requires-Dist: pytest-cov>=4.0; extra == 'dev'
Requires-Dist: pytest>=7.0; extra == 'dev'
